inpoly_cython/LICENSE
inpoly_cython/README.MD
inpoly_cython/__init__.py
inpoly_cython/requirements.txt
inpoly_cython/thirdparty.json
inpoly_cython-0.10.dist-info/LICENSE.rst
inpoly_cython-0.10.dist-info/METADATA
inpoly_cython-0.10.dist-info/WHEEL
inpoly_cython-0.10.dist-info/top_level.txt
inpoly_cython-0.10.dist-info/RECORD
