Metadata-Version: 2.1
Name: inpoly-cython
Version: 0.10
Summary: inpoly-cython / Original: https://github.com/dengwirda/inpoly-python
Home-page: https://github.com/hansalemaos/inpoly_cython
Author: Johannes Fischer
Author-email: <aulasparticularesdealemaosp@gmail.com>
License: MPL
Keywords: polygon,intersect
Classifier: Development Status :: 4 - Beta
Classifier: Programming Language :: Python :: 3 :: Only
Classifier: Programming Language :: Python :: 3.9
Classifier: Topic :: Scientific/Engineering :: Visualization
Classifier: Topic :: Software Development :: Libraries :: Python Modules
Classifier: Topic :: Text Editors :: Text Processing
Classifier: Topic :: Text Processing :: General
Classifier: Topic :: Text Processing :: Indexing
Classifier: Topic :: Text Processing :: Filters
Classifier: Topic :: Utilities
License-File: LICENSE.rst
Requires-Dist: Cython
Requires-Dist: numpy
